mswappinit/__init__.py
mswappinit/py.typed
mswappinit/quick_db.py
mswappinit-2025.4.30.dist-info/METADATA
mswappinit-2025.4.30.dist-info/WHEEL
mswappinit-2025.4.30.dist-info/RECORD
