Metadata-Version: 2.4
Name: mswappinit
Version: 2025.4.30
Summary: a personal, opinionated python app initializer
Project-URL: Homepage, https://github.com/mwartell/mswappinit
Project-URL: Source, https://github.com/mwartell/mswappinit
Author-email: matt wartell <matt.wartel@gmail.com>
Requires-Python: >=3.12
Requires-Dist: loguru>=0.7
Requires-Dist: pickledb>=1.3.2
Requires-Dist: python-dotenv>=1.1.0
